layla/__init__.py
layla/layla.py
layla/model/__init__.py
layla/model/model.py
layla/model/window_gru.py
layla/stream/__init__.py
layla/stream/input.py
layla/stream/stream.py
layla-0.0.2.dist-info/LICENSE.TXT
layla-0.0.2.dist-info/METADATA
layla-0.0.2.dist-info/WHEEL
layla-0.0.2.dist-info/top_level.txt
layla-0.0.2.dist-info/RECORD
