Metadata-Version: 2.1
Name: layla
Version: 0.0.2
Summary: Deep learning package for automating experimentation, prototyping and tuning
Home-page: https://asimbluemoon@bitbucket.org/laylaelectric/ml.git
Author: Mohammad Asim
Author-email: asim.98.12.26@gmail.com
License: LICENSE.txt
Keywords: python,layla
Platform: UNKNOWN
Classifier: Development Status :: 1 - Planning
Classifier: Programming Language :: Python :: 3
Classifier: Operating System :: OS Independent
Requires-Python: >=3.6
License-File: LICENSE.TXT
Requires-Dist: tensorflow (>=2.3)
